pymare/__init__.py
pymare/_version.py
pymare/core.py
pymare/results.py
pymare/stats.py
pymare/utils.py
pymare/datasets/__init__.py
pymare/datasets/metadat.py
pymare/effectsize/__init__.py
pymare/effectsize/base.py
pymare/effectsize/expressions.json
pymare/effectsize/expressions.py
pymare/estimators/__init__.py
pymare/estimators/combination.py
pymare/estimators/estimators.py
pymare/resources/datasets/michael2013.json
pymare/resources/datasets/michael2013.tsv
PyMARE-0.0.10.dist-info/LICENSE
PyMARE-0.0.10.dist-info/METADATA
PyMARE-0.0.10.dist-info/WHEEL
PyMARE-0.0.10.dist-info/top_level.txt
PyMARE-0.0.10.dist-info/RECORD
